{"response": {"termsofService": "http://www.wunderground.com/weather/api/d/terms.html", "version": "0.1", "features": {"history": 1}}, "history": {"date": {"mday": "27", "hour": "00", "min": "00", "mon": "11", "pretty": "November 27, 2014", "year": "2014", "tzname": "Europe/Copenhagen"}, "utcdate": {"mday": "26", "hour": "23", "min": "00", "mon": "11", "pretty": "November 26, 2014", "year": "2014", "tzname": "UTC"}, "observations": [{"heatindexm": "-9999", "windchillm": "-999", "wdire": "SE", "wdird": "140", "windchilli": "-999", "hail": "0", "heatindexi": "-9999", "precipi": "", "thunder": "0", "pressurei": "30.18", "snow": "0", "pressurem": "1022", "fog": "0", "icon": "mostlycloudy", "precipm": "", "conds": "Mostly Cloudy", "tornado": "0", "hum": "87", "tempi": "41", "tempm": "5", "dewptm": "4", "rain": "0", "dewpti": "38", "date": {"mday": "27", "hour": "00", "min": "00", "mon": "11", "pretty": "12:00 AM CET on November 27, 2014", "year": "2014", "tzname": "Europe/Copenhagen"}, "visi": "14", "vism": "23", "utcdate": {"mday": "26", "hour": "23", "min": "00", "mon": "11", "pretty": "11:00 PM GMT on November 26, 2014", "year": "2014", "tzname": "UTC"}, "wgusti": "", "metar": "AAXX 26234 06156 45573 71404 10052 20036 30202 40219 57009 333 55300 20000 85/22 87/26", "wgustm": "", "wspdi": "4.6", "wspdm": "7.4"}, {"heatindexm": "-9999", "windchillm": "-999", "wdire": "East", "wdird": "100", "windchilli": "-999", "hail": "0", "heatindexi": "-9999", "precipi": "", "thunder": "0", "pressurei": "30.17", "snow": "0", "pressurem": "1022", "fog": "0", "icon": "mostlycloudy", "precipm": "", "conds": "Mostly Cloudy", "tornado": "0", "hum": "86", "tempi": "41", "tempm": "5", "dewptm": "4", "rain": "0", "dewpti": "38", "date": {"mday": "27", "hour": "01", "min": "00", "mon": "11", "pretty": "1:00 AM CET on November 27, 2014", "year": "2014", "tzname": "Europe/Copenhagen"}, "visi": "11", "vism": "18", "utcdate": {"mday": "27", "hour": "00", "min": "00", "mon": "11", "pretty": "12:00 AM GMT on November 27, 2014", "year": "2014", "tzname": "UTC"}, "wgusti": "", "metar": "AAXX 27004 06156 05568 51004 10049 20035 30198 40215 57011 6///1 333 55300 20000 6///7 85/24", "wgustm": "", "wspdi": "4.6", "wspdm": "7.4"}, {"heatindexm": "-9999", "windchillm": "-999", "wdire": "East", "wdird": "100", "windchilli": "-999", "hail": "0", "heatindexi": "-9999", "precipi": "", "thunder": "0", "pressurei": "30.16", "snow": "0", "pressurem": "1021", "fog": "0", "icon": "partlycloudy", "precipm": "", "conds": "Scattered Clouds", "tornado": "0", "hum": "89", "tempi": "39", "tempm": "4", "dewptm": "3", "rain": "0", "dewpti": "37", "date": {"mday": "27", "hour": "02", "min": "00", "mon": "11", "pretty": "2:00 AM CET on November 27, 2014", "year": "2014", "tzname": "Europe/Copenhagen"}, "visi": "9", "vism": "14", "utcdate": {"mday": "27", "hour": "01", "min": "00", "mon": "11", "pretty": "1:00 AM GMT on November 27, 2014", "year": "2014", "tzname": "UTC"}, "wgusti": "", "metar": "AAXX 27014 06156 45564 11005 10038 20027 30194 40211 57012 333 55300 20000 81/26", "wgustm": "", "wspdi": "5.8", "wspdm": "9.3"}, {"heatindexm": "-9999", "windchillm": "-999", "wdire": "East", "wdird": "100", "windchilli": "-999", "hail": "0", "heatindexi": "-9999", "precipi": "", "thunder": "0", "pressurei": "30.14", "snow": "0", "pressurem": "1021", "fog": "0", "icon": "", "precipm": "", "conds": "", "tornado": "0", "hum": "92", "tempi": "36", "tempm": "2", "dewptm": "1", "rain": "0", "dewpti": "35", "date": {"mday": "27", "hour": "03", "min": "00", "mon": "11", "pretty": "3:00 AM CET on November 27, 2014", "year": "2014", "tzname": "Europe/Copenhagen"}, "visi": "6", "vism": "10", "utcdate": {"mday": "27", "hour": "02", "min": "00", "mon": "11", "pretty": "2:00 AM GMT on November 27, 2014", "year": "2014", "tzname": "UTC"}, "wgusti": "", "metar": "AAXX 27024 06156 45/60 01003 10022 20014 30190 40207 57012 333 55300 20000", "wgustm": "", "wspdi": "3.5", "wspdm": "5.6"}, {"heatindexm": "-9999", "windchillm": "-999", "wdire": "SSE", "wdird": "160", "windchilli": "-999", "hail": "0", "heatindexi": "-9999", "precipi": "", "thunder": "0", "pressurei": "30.14", "snow": "0", "pressurem": "1020", "fog": "0", "icon": "clear", "precipm": "", "conds": "Clear", "tornado": "0", "hum": "92", "tempi": "37", "tempm": "3", "dewptm": "2", "rain": "0", "dewpti": "36", "date": {"mday": "27", "hour": "04", "min": "00", "mon": "11", "pretty": "4:00 AM CET on November 27, 2014", "year": "2014", "tzname": "Europe/Copenhagen"}, "visi": "6", "vism": "10", "utcdate": {"mday": "27", "hour": "03", "min": "00", "mon": "11", "pretty": "3:00 AM GMT on November 27, 2014", "year": "2014", "tzname": "UTC"}, "wgusti": "", "metar": "AAXX 27034 06156 27460 31605 10026 20020 30187 40204 57011 70010 333 55300 20000 6///7 81/18 83/22", "wgustm": "", "wspdi": "5.8", "wspdm": "9.3"}, {"heatindexm": "-9999", "windchillm": "-999", "wdire": "East", "wdird": "100", "windchilli": "-999", "hail": "0", "heatindexi": "-9999", "precipi": "", "thunder": "0", "pressurei": "30.12", "snow": "0", "pressurem": "1020", "fog": "0", "icon": "hazy", "precipm": "", "conds": "Mist", "tornado": "0", "hum": "97", "tempi": "35", "tempm": "2", "dewptm": "1", "rain": "0", "dewpti": "35", "date": {"mday": "27", "hour": "05", "min": "00", "mon": "11", "pretty": "5:00 AM CET on November 27, 2014", "year": "2014", "tzname": "Europe/Copenhagen"}, "visi": "4", "vism": "7", "utcdate": {"mday": "27", "hour": "04", "min": "00", "mon": "11", "pretty": "4:00 AM GMT on November 27, 2014", "year": "2014", "tzname": "UTC"}, "wgusti": "", "metar": "AAXX 27044 06156 47557 11003 10019 20014 30183 40200 57011 71011 333 55300 20000 81/20", "wgustm": "", "wspdi": "3.5", "wspdm": "5.6"}, {"heatindexm": "-9999", "windchillm": "-999", "wdire": "East", "wdird": "100", "windchilli": "-999", "hail": "0", "heatindexi": "-9999", "precipi": "", "thunder": "0", "pressurei": "30.11", "snow": "0", "pressurem": "1020", "fog": "0", "icon": "hazy", "precipm": "", "conds": "Mist", "tornado": "0", "hum": "93", "tempi": "36", "tempm": "2", "dewptm": "2", "rain": "0", "dewpti": "35", "date": {"mday": "27", "hour": "06", "min": "00", "mon": "11", "pretty": "6:00 AM CET on November 27, 2014", "year": "2014", "tzname": "Europe/Copenhagen"}, "visi": "6", "vism": "9", "utcdate": {"mday": "27", "hour": "05", "min": "00", "mon": "11", "pretty": "5:00 AM GMT on November 27, 2014", "year": "2014", "tzname": "UTC"}, "wgusti": "", "metar": "AAXX 27054 06156 47/59 01006 10023 20015 30179 40196 57011 71011 333 55300 20000", "wgustm": "", "wspdi": "6.9", "wspdm": "11.1"}, {"heatindexm": "-9999", "windchillm": "-999", "wdire": "East", "wdird": "100", "windchilli": "-999", "hail": "0", "heatindexi": "-9999", "precipi": "", "thunder": "0", "pressurei": "30.10", "snow": "0", "pressurem": "1019", "fog": "0", "icon": "clear", "precipm": "", "conds": "Clear", "tornado": "0", "hum": "85", "tempi": "39", "tempm": "4", "dewptm": "2", "rain": "0", "dewpti": "36", "date": {"mday": "27", "hour": "07", "min": "00", "mon": "11", "pretty": "7:00 AM CET on November 27, 2014", "year": "2014", "tzname": "Europe/Copenhagen"}, "visi": "7", "vism": "11", "utcdate": {"mday": "27", "hour": "06", "min": "00", "mon": "11", "pretty": "6:00 AM GMT on November 27, 2014", "year": "2014", "tzname": "UTC"}, "wgusti": "", "metar": "AAXX 27064 06156 07561 11008 10037 20023 30177 40193 57010 6///2 70010 333 10058 20018 55300 20000 6///7 70000 81/26", "wgustm": "", "wspdi": "9.2", "wspdm": "14.8"}, {"heatindexm": "-9999", "windchillm": "-999", "wdire": "East", "wdird": "100", "windchilli": "-999", "hail": "0", "heatindexi": "-9999", "precipi": "", "thunder": "0", "pressurei": "30.11", "snow": "0", "pressurem": "1020", "fog": "0", "icon": "hazy", "precipm": "", "conds": "Mist", "tornado": "0", "hum": "92", "tempi": "37", "tempm": "3", "dewptm": "2", "rain": "0", "dewpti": "36", "date": {"mday": "27", "hour": "08", "min": "00", "mon": "11", "pretty": "8:00 AM CET on November 27, 2014", "year": "2014", "tzname": "Europe/Copenhagen"}, "visi": "5", "vism": "8", "utcdate": {"mday": "27", "hour": "07", "min": "00", "mon": "11", "pretty": "7:00 AM GMT on November 27, 2014", "year": "2014", "tzname": "UTC"}, "wgusti": "", "metar": "AAXX 27074 06156 47658 11006 10030 20020 30179 40196 57004 71010 333 55300 20000 81/35", "wgustm": "", "wspdi": "6.9", "wspdm": "11.1"}, {"heatindexm": "-9999", "windchillm": "-999", "wdire": "East", "wdird": "100", "windchilli": "-999", "hail": "0", "heatindexi": "-9999", "precipi": "", "thunder": "0", "pressurei": "30.12", "snow": "0", "pressurem": "1020", "fog": "0", "icon": "hazy", "precipm": "", "conds": "Mist", "tornado": "0", "hum": "87", "tempi": "39", "tempm": "4", "dewptm": "2", "rain": "0", "dewpti": "36", "date": {"mday": "27", "hour": "09", "min": "00", "mon": "11", "pretty": "9:00 AM CET on November 27, 2014", "year": "2014", "tzname": "Europe/Copenhagen"}, "visi": "6", "vism": "9", "utcdate": {"mday": "27", "hour": "08", "min": "00", "mon": "11", "pretty": "8:00 AM GMT on November 27, 2014", "year": "2014", "tzname": "UTC"}, "wgusti": "", "metar": "AAXX 27084 06156 47659 11006 10037 20025 30182 40199 52003 71011 333 55300 20065 81/34", "wgustm": "", "wspdi": "6.9", "wspdm": "11.1"}, {"heatindexm": "-9999", "windchillm": "-999", "wdire": "ESE", "wdird": "110", "windchilli": "-999", "hail": "0", "heatindexi": "-9999", "precipi": "", "thunder": "0", "pressurei": "30.12", "snow": "0", "pressurem": "1020", "fog": "0", "icon": "clear", "precipm": "", "conds": "Clear", "tornado": "0", "hum": "79", "tempi": "40", "tempm": "5", "dewptm": "2", "rain": "0", "dewpti": "36", "date": {"mday": "27", "hour": "10", "min": "00", "mon": "11", "pretty": "10:00 AM CET on November 27, 2014", "year": "2014", "tzname": "Europe/Copenhagen"}, "visi": "9", "vism": "14", "utcdate": {"mday": "27", "hour": "09", "min": "00", "mon": "11", "pretty": "9:00 AM GMT on November 27, 2014", "year": "2014", "tzname": "UTC"}, "wgusti": "", "metar": "AAXX 27094 06156 27/64 01108 10046 20021 30183 40200 52006 70010 333 55310 20320 6///7", "wgustm": "", "wspdi": "9.2", "wspdm": "14.8"}, {"heatindexm": "-9999", "windchillm": "-999", "wdire": "East", "wdird": "100", "windchilli": "-999", "hail": "0", "heatindexi": "-9999", "precipi": "", "thunder": "0", "pressurei": "30.11", "snow": "0", "pressurem": "1020", "fog": "0", "icon": "", "precipm": "", "conds": "", "tornado": "0", "hum": "73", "tempi": "42", "tempm": "6", "dewptm": "2", "rain": "0", "dewpti": "36", "date": {"mday": "27", "hour": "11", "min": "00", "mon": "11", "pretty": "11:00 AM CET on November 27, 2014", "year": "2014", "tzname": "Europe/Copenhagen"}, "visi": "9", "vism": "15", "utcdate": {"mday": "27", "hour": "10", "min": "00", "mon": "11", "pretty": "10:00 AM GMT on November 27, 2014", "year": "2014", "tzname": "UTC"}, "wgusti": "", "metar": "AAXX 27104 06156 45/65 01010 10058 20024 30179 40196 54000 333 55310 20576", "wgustm": "", "wspdi": "11.5", "wspdm": "18.5"}, {"heatindexm": "-9999", "windchillm": "-999", "wdire": "East", "wdird": "100", "windchilli": "-999", "hail": "0", "heatindexi": "-9999", "precipi": "", "thunder": "0", "pressurei": "30.10", "snow": "0", "pressurem": "1019", "fog": "0", "icon": "", "precipm": "", "conds": "", "tornado": "0", "hum": "62", "tempi": "44", "tempm": "7", "dewptm": "2", "rain": "0", "dewpti": "35", "date": {"mday": "27", "hour": "12", "min": "00", "mon": "11", "pretty": "12:00 PM CET on November 27, 2014", "year": "2014", "tzname": "Europe/Copenhagen"}, "visi": "14", "vism": "23", "utcdate": {"mday": "27", "hour": "11", "min": "00", "mon": "11", "pretty": "11:00 AM GMT on November 27, 2014", "year": "2014", "tzname": "UTC"}, "wgusti": "", "metar": "AAXX 27114 06156 45/73 01011 10067 20018 30176 40192 57006 333 55310 20731", "wgustm": "", "wspdi": "12.7", "wspdm": "20.4"}, {"heatindexm": "-9999", "windchillm": "-999", "wdire": "ESE", "wdird": "110", "windchilli": "-999", "hail": "0", "heatindexi": "-9999", "precipi": "", "thunder": "0", "pressurei": "30.09", "snow": "0", "pressurem": "1019", "fog": "0", "icon": "clear", "precipm": "", "conds": "Clear", "tornado": "0", "hum": "59", "tempi": "44", "tempm": "7", "dewptm": "1", "rain": "0", "dewpti": "35", "date": {"mday": "27", "hour": "13", "min": "00", "mon": "11", "pretty": "1:00 PM CET on November 27, 2014", "year": "2014", "tzname": "Europe/Copenhagen"}, "visi": "18", "vism": "29", "utcdate": {"mday": "27", "hour": "12", "min": "00", "mon": "11", "pretty": "12:00 PM GMT on November 27, 2014", "year": "2014", "tzname": "UTC"}, "wgusti": "", "metar": "AAXX 27124 06156 07/79 01113 10069 20014 30172 40188 57011 6///1 70010 333 55310 20742 6///7", "wgustm": "", "wspdi": "15.0", "wspdm": "24.1"}, {"heatindexm": "-9999", "windchillm": "-999", "wdire": "East", "wdird": "100", "windchilli": "-999", "hail": "0", "heatindexi": "-9999", "precipi": "", "thunder": "0", "pressurei": "30.08", "snow": "0", "pressurem": "1019", "fog": "0", "icon": "", "precipm": "", "conds": "", "tornado": "0", "hum": "59", "tempi": "44", "tempm": "7", "dewptm": "1", "rain": "0", "dewpti": "34", "date": {"mday": "27", "hour": "14", "min": "00", "mon": "11", "pretty": "2:00 PM CET on November 27, 2014", "year": "2014", "tzname": "Europe/Copenhagen"}, "visi": "16", "vism": "25", "utcdate": {"mday": "27", "hour": "13", "min": "00", "mon": "11", "pretty": "1:00 PM GMT on November 27, 2014", "year": "2014", "tzname": "UTC"}, "wgusti": "", "metar": "AAXX 27134 06156 45/75 01012 10066 20013 30169 40186 57010 333 55310 20612", "wgustm": "", "wspdi": "13.8", "wspdm": "22.2"}, {"heatindexm": "-9999", "windchillm": "-999", "wdire": "East", "wdird": "100", "windchilli": "-999", "hail": "0", "heatindexi": "-9999", "precipi": "", "thunder": "0", "pressurei": "30.08", "snow": "0", "pressurem": "1019", "fog": "0", "icon": "", "precipm": "", "conds": "", "tornado": "0", "hum": "61", "tempi": "43", "tempm": "6", "dewptm": "1", "rain": "0", "dewpti": "34", "date": {"mday": "27", "hour": "15", "min": "00", "mon": "11", "pretty": "3:00 PM CET on November 27, 2014", "year": "2014", "tzname": "Europe/Copenhagen"}, "visi": "16", "vism": "26", "utcdate": {"mday": "27", "hour": "14", "min": "00", "mon": "11", "pretty": "2:00 PM GMT on November 27, 2014", "year": "2014", "tzname": "UTC"}, "wgusti": "", "metar": "AAXX 27144 06156 45/76 01010 10059 20012 30169 40186 57007 333 55310 20328", "wgustm": "", "wspdi": "11.5", "wspdm": "18.5"}, {"heatindexm": "-9999", "windchillm": "-999", "wdire": "East", "wdird": "100", "windchilli": "-999", "hail": "0", "heatindexi": "-9999", "precipi": "", "thunder": "0", "pressurei": "30.09", "snow": "0", "pressurem": "1019", "fog": "0", "icon": "", "precipm": "", "conds": "", "tornado": "0", "hum": "68", "tempi": "41", "tempm": "5", "dewptm": "1", "rain": "0", "dewpti": "34", "date": {"mday": "27", "hour": "16", "min": "00", "mon": "11", "pretty": "4:00 PM CET on November 27, 2014", "year": "2014", "tzname": "Europe/Copenhagen"}, "visi": "14", "vism": "23", "utcdate": {"mday": "27", "hour": "15", "min": "00", "mon": "11", "pretty": "3:00 PM GMT on November 27, 2014", "year": "2014", "tzname": "UTC"}, "wgusti": "", "metar": "AAXX 27154 06156 25/73 01008 10048 20011 30171 40187 57001 333 55302 20068 6///7", "wgustm": "", "wspdi": "9.2", "wspdm": "14.8"}, {"heatindexm": "-9999", "windchillm": "-999", "wdire": "ESE", "wdird": "110", "windchilli": "-999", "hail": "0", "heatindexi": "-9999", "precipi": "", "thunder": "0", "pressurei": "30.09", "snow": "0", "pressurem": "1019", "fog": "0", "icon": "", "precipm": "", "conds": "", "tornado": "0", "hum": "76", "tempi": "39", "tempm": "4", "dewptm": "1", "rain": "0", "dewpti": "34", "date": {"mday": "27", "hour": "17", "min": "00", "mon": "11", "pretty": "5:00 PM CET on November 27, 2014", "year": "2014", "tzname": "Europe/Copenhagen"}, "visi": "9", "vism": "15", "utcdate": {"mday": "27", "hour": "16", "min": "00", "mon": "11", "pretty": "4:00 PM GMT on November 27, 2014", "year": "2014", "tzname": "UTC"}, "wgusti": "", "metar": "AAXX 27164 06156 45/65 01108 10041 20012 30173 40189 52004 333 55300 20000", "wgustm": "", "wspdi": "9.2", "wspdm": "14.8"}, {"heatindexm": "-9999", "windchillm": "-999", "wdire": "East", "wdird": "100", "windchilli": "-999", "hail": "0", "heatindexi": "-9999", "precipi": "", "thunder": "0", "pressurei": "30.10", "snow": "0", "pressurem": "1019", "fog": "0", "icon": "", "precipm": "", "conds": "", "tornado": "0", "hum": "80", "tempi": "38", "tempm": "4", "dewptm": "1", "rain": "0", "dewpti": "34", "date": {"mday": "27", "hour": "18", "min": "00", "mon": "11", "pretty": "6:00 PM CET on November 27, 2014", "year": "2014", "tzname": "Europe/Copenhagen"}, "visi": "11", "vism": "17", "utcdate": {"mday": "27", "hour": "17", "min": "00", "mon": "11", "pretty": "5:00 PM GMT on November 27, 2014", "year": "2014", "tzname": "UTC"}, "wgusti": "", "metar": "AAXX 27174 06156 45/67 /1006 10035 20011 30175 40192 52006 333 55300 20000", "wgustm": "", "wspdi": "6.9", "wspdm": "11.1"}, {"heatindexm": "-9999", "windchillm": "-999", "wdire": "East", "wdird": "80", "windchilli": "-999", "hail": "0", "heatindexi": "-9999", "precipi": "", "thunder": "0", "pressurei": "30.11", "snow": "0", "pressurem": "1019", "fog": "0", "icon": "partlycloudy", "precipm": "", "conds": "Partly Cloudy", "tornado": "0", "hum": "89", "tempi": "38", "tempm": "3", "dewptm": "2", "rain": "0", "dewpti": "36", "date": {"mday": "27", "hour": "19", "min": "00", "mon": "11", "pretty": "7:00 PM CET on November 27, 2014", "year": "2014", "tzname": "Europe/Copenhagen"}, "visi": "9", "vism": "15", "utcdate": {"mday": "27", "hour": "18", "min": "00", "mon": "11", "pretty": "6:00 PM GMT on November 27, 2014", "year": "2014", "tzname": "UTC"}, "wgusti": "", "metar": "AAXX 27184 06156 05665 30806 10034 20022 30177 40194 52006 6///2 333 10069 20026 55300 20000 6///7 83/38", "wgustm": "", "wspdi": "6.9", "wspdm": "11.1"}, {"heatindexm": "-9999", "windchillm": "-999", "wdire": "East", "wdird": "90", "windchilli": "-999", "hail": "0", "heatindexi": "-9999", "precipi": "", "thunder": "0", "pressurei": "30.12", "snow": "0", "pressurem": "1020", "fog": "0", "icon": "partlycloudy", "precipm": "", "conds": "Scattered Clouds", "tornado": "0", "hum": "86", "tempi": "40", "tempm": "4", "dewptm": "3", "rain": "0", "dewpti": "37", "date": {"mday": "27", "hour": "20", "min": "00", "mon": "11", "pretty": "8:00 PM CET on November 27, 2014", "year": "2014", "tzname": "Europe/Copenhagen"}, "visi": "9", "vism": "15", "utcdate": {"mday": "27", "hour": "19", "min": "00", "mon": "11", "pretty": "7:00 PM GMT on November 27, 2014", "year": "2014", "tzname": "UTC"}, "wgusti": "", "metar": "AAXX 27194 06156 45665 10910 10042 20029 30180 40197 52007 333 55300 20000 81/41", "wgustm": "", "wspdi": "11.5", "wspdm": "18.5"}, {"heatindexm": "-9999", "windchillm": "-999", "wdire": "East", "wdird": "90", "windchilli": "-999", "hail": "0", "heatindexi": "-9999", "precipi": "", "thunder": "0", "pressurei": "30.13", "snow": "0", "pressurem": "1020", "fog": "0", "icon": "", "precipm": "", "conds": "", "tornado": "0", "hum": "91", "tempi": "39", "tempm": "4", "dewptm": "3", "rain": "0", "dewpti": "37", "date": {"mday": "27", "hour": "21", "min": "00", "mon": "11", "pretty": "9:00 PM CET on November 27, 2014", "year": "2014", "tzname": "Europe/Copenhagen"}, "visi": "7", "vism": "11", "utcdate": {"mday": "27", "hour": "20", "min": "00", "mon": "11", "pretty": "8:00 PM GMT on November 27, 2014", "year": "2014", "tzname": "UTC"}, "wgusti": "", "metar": "AAXX 27204 06156 45/61 00910 10040 20029 30184 40201 52009 333 55300 20000", "wgustm": "", "wspdi": "11.5", "wspdm": "18.5"}, {"heatindexm": "-9999", "windchillm": "-999", "wdire": "East", "wdird": "90", "windchilli": "-999", "hail": "0", "heatindexi": "-9999", "precipi": "", "thunder": "0", "pressurei": "30.13", "snow": "0", "pressurem": "1020", "fog": "0", "icon": "clear", "precipm": "", "conds": "Clear", "tornado": "0", "hum": "89", "tempi": "39", "tempm": "4", "dewptm": "3", "rain": "0", "dewpti": "37", "date": {"mday": "27", "hour": "22", "min": "00", "mon": "11", "pretty": "10:00 PM CET on November 27, 2014", "year": "2014", "tzname": "Europe/Copenhagen"}, "visi": "6", "vism": "10", "utcdate": {"mday": "27", "hour": "21", "min": "00", "mon": "11", "pretty": "9:00 PM GMT on November 27, 2014", "year": "2014", "tzname": "UTC"}, "wgusti": "", "metar": "AAXX 27214 06156 27/60 00911 10039 20027 30187 40203 52010 70010 333 55300 20000 6///7", "wgustm": "", "wspdi": "12.7", "wspdm": "20.4"}, {"heatindexm": "-9999", "windchillm": "-999", "wdire": "East", "wdird": "90", "windchilli": "-999", "hail": "0", "heatindexi": "-9999", "precipi": "", "thunder": "0", "pressurei": "30.14", "snow": "0", "pressurem": "1020", "fog": "0", "icon": "", "precipm": "", "conds": "", "tornado": "0", "hum": "92", "tempi": "39", "tempm": "4", "dewptm": "3", "rain": "0", "dewpti": "37", "date": {"mday": "27", "hour": "23", "min": "00", "mon": "11", "pretty": "11:00 PM CET on November 27, 2014", "year": "2014", "tzname": "Europe/Copenhagen"}, "visi": "7", "vism": "11", "utcdate": {"mday": "27", "hour": "22", "min": "00", "mon": "11", "pretty": "10:00 PM GMT on November 27, 2014", "year": "2014", "tzname": "UTC"}, "wgusti": "", "metar": "AAXX 27224 06156 45/61 00911 10041 20030 30187 40204 52007 333 55300 20000", "wgustm": "", "wspdi": "12.7", "wspdm": "20.4"}], "dailysummary": [{"maxpressurem": "1022", "maxdewptm": "4", "maxpressurei": "30.18", "maxdewpti": "38", "since1julheatingdegreedaysnormal": "", "heatingdegreedaysnormal": "", "since1sepcoolingdegreedaysnormal": "", "hail": "0", "since1julsnowfallm": "", "date": {"mday": "27", "hour": "00", "min": "00", "mon": "11", "pretty": "12:00 AM CET on November 27, 2014", "year": "2014", "tzname": "Europe/Copenhagen"}, "since1julheatingdegreedays": "", "maxvisi": "18.0", "since1sepheatingdegreedaysnormal": "", "heatingdegreedays": "26", "mindewptm": "1", "since1sepheatingdegreedays": "", "maxwspdm": "24", "since1julsnowfalli": "", "since1sepcoolingdegreedays": "", "snow": "0", "meanvism": "15.3", "meandewptm": "2", "snowdepthm": "", "meanvisi": "9.5", "fog": "0", "snowdepthi": "", "minvism": "7.0", "since1jancoolingdegreedays": "", "minvisi": "4.0", "coolingdegreedaysnormal": "", "gdegreedays": "0", "maxwspdi": "15", "meanwindspdi": "7", "meanpressurei": "30.12", "monthtodateheatingdegreedaysnormal": "", "meanwindspdm": "11", "meanpressurem": "1019.87", "tornado": "0", "mindewpti": "34", "mintempi": "35", "meandewpti": "36", "rain": "0", "mintempm": "1", "minhumidity": "59", "precipsource": "3Or6HourObs", "minwspdi": "4", "meanwdird": "-1", "meanwdire": "Variable", "minwspdm": "6", "monthtodatesnowfalli": "", "monthtodatecoolingdegreedaysnormal": "", "monthtodatesnowfallm": "", "maxhumidity": "97", "coolingdegreedays": "0", "maxtempm": "6", "minpressurei": "30.08", "monthtodatecoolingdegreedays": "", "maxtempi": "44", "minpressurem": "1019", "humidity": "82", "precipi": "0.00", "snowfalli": "", "since1jancoolingdegreedaysnormal": "", "precipm": "0.0", "snowfallm": "", "thunder": "0", "monthtodateheatingdegreedays": "", "meantempi": "40", "maxvism": "29.0", "meantempm": "4"}]}}