{"response": {"termsofService": "http://www.wunderground.com/weather/api/d/terms.html", "version": "0.1", "features": {"history": 1}}, "history": {"date": {"mday": "05", "hour": "00", "min": "00", "mon": "09", "pretty": "September 5, 2014", "year": "2014", "tzname": "Europe/Copenhagen"}, "utcdate": {"mday": "04", "hour": "22", "min": "00", "mon": "09", "pretty": "September 4, 2014", "year": "2014", "tzname": "UTC"}, "observations": [{"heatindexm": "-9999", "windchillm": "-999", "wdire": "ENE", "wdird": "70", "windchilli": "-999", "hail": "0", "heatindexi": "-9999", "precipi": "", "thunder": "0", "pressurei": "30.23", "snow": "0", "pressurem": "1024", "fog": "0", "icon": "", "precipm": "", "conds": "", "tornado": "0", "hum": "84", "tempi": "55", "tempm": "13", "dewptm": "11", "rain": "0", "dewpti": "52", "date": {"mday": "05", "hour": "00", "min": "00", "mon": "09", "pretty": "12:00 AM CEST on September 05, 2014", "year": "2014", "tzname": "Europe/Copenhagen"}, "visi": "19", "vism": "30", "utcdate": {"mday": "04", "hour": "22", "min": "00", "mon": "09", "pretty": "10:00 PM GMT on September 04, 2014", "year": "2014", "tzname": "UTC"}, "wgusti": "", "metar": "AAXX 04224 06156 45/80 00706 10126 20109 30219 40236 57007 333 55300 20000", "wgustm": "", "wspdi": "6.9", "wspdm": "11.1"}, {"heatindexm": "-9999", "windchillm": "-999", "wdire": "ENE", "wdird": "70", "windchilli": "-999", "hail": "0", "heatindexi": "-9999", "precipi": "", "thunder": "0", "pressurei": "30.22", "snow": "0", "pressurem": "1023", "fog": "0", "icon": "", "precipm": "", "conds": "", "tornado": "0", "hum": "89", "tempi": "54", "tempm": "12", "dewptm": "11", "rain": "0", "dewpti": "52", "date": {"mday": "05", "hour": "01", "min": "00", "mon": "09", "pretty": "1:00 AM CEST on September 05, 2014", "year": "2014", "tzname": "Europe/Copenhagen"}, "visi": "14", "vism": "23", "utcdate": {"mday": "04", "hour": "23", "min": "00", "mon": "09", "pretty": "11:00 PM GMT on September 04, 2014", "year": "2014", "tzname": "UTC"}, "wgusti": "", "metar": "AAXX 04234 06156 45/73 00705 10120 20109 30215 40232 57006 333 55300 20000", "wgustm": "", "wspdi": "5.8", "wspdm": "9.3"}, {"heatindexm": "-9999", "windchillm": "-999", "wdire": "ENE", "wdird": "70", "windchilli": "-999", "hail": "0", "heatindexi": "-9999", "precipi": "", "thunder": "0", "pressurei": "30.20", "snow": "0", "pressurem": "1023", "fog": "0", "icon": "", "precipm": "", "conds": "", "tornado": "0", "hum": "94", "tempi": "53", "tempm": "12", "dewptm": "11", "rain": "0", "dewpti": "52", "date": {"mday": "05", "hour": "02", "min": "00", "mon": "09", "pretty": "2:00 AM CEST on September 05, 2014", "year": "2014", "tzname": "Europe/Copenhagen"}, "visi": "11", "vism": "18", "utcdate": {"mday": "05", "hour": "00", "min": "00", "mon": "09", "pretty": "12:00 AM GMT on September 05, 2014", "year": "2014", "tzname": "UTC"}, "wgusti": "", "metar": "AAXX 05004 06156 05/68 00705 10116 20110 30210 40227 57010 6///1 333 55300 20000 6///7", "wgustm": "", "wspdi": "5.8", "wspdm": "9.3"}, {"heatindexm": "-9999", "windchillm": "-999", "wdire": "NE", "wdird": "50", "windchilli": "-999", "hail": "0", "heatindexi": "-9999", "precipi": "", "thunder": "0", "pressurei": "30.19", "snow": "0", "pressurem": "1022", "fog": "0", "icon": "", "precipm": "", "conds": "", "tornado": "0", "hum": "98", "tempi": "52", "tempm": "11", "dewptm": "11", "rain": "0", "dewpti": "52", "date": {"mday": "05", "hour": "03", "min": "00", "mon": "09", "pretty": "3:00 AM CEST on September 05, 2014", "year": "2014", "tzname": "Europe/Copenhagen"}, "visi": "8", "vism": "13", "utcdate": {"mday": "05", "hour": "01", "min": "00", "mon": "09", "pretty": "1:00 AM GMT on September 05, 2014", "year": "2014", "tzname": "UTC"}, "wgusti": "", "metar": "AAXX 05014 06156 45/63 00504 10112 20109 30205 40222 57014 333 55300 20000", "wgustm": "", "wspdi": "4.6", "wspdm": "7.4"}, {"heatindexm": "-9999", "windchillm": "-999", "wdire": "NE", "wdird": "40", "windchilli": "-999", "hail": "0", "heatindexi": "-9999", "precipi": "", "thunder": "0", "pressurei": "30.17", "snow": "0", "pressurem": "1022", "fog": "0", "icon": "mostlycloudy", "precipm": "", "conds": "Mostly Cloudy", "tornado": "0", "hum": "97", "tempi": "54", "tempm": "12", "dewptm": "12", "rain": "0", "dewpti": "53", "date": {"mday": "05", "hour": "04", "min": "00", "mon": "09", "pretty": "4:00 AM CEST on September 05, 2014", "year": "2014", "tzname": "Europe/Copenhagen"}, "visi": "6", "vism": "10", "utcdate": {"mday": "05", "hour": "02", "min": "00", "mon": "09", "pretty": "2:00 AM GMT on September 05, 2014", "year": "2014", "tzname": "UTC"}, "wgusti": "", "metar": "AAXX 05024 06156 45260 50404 10120 20119 30199 40216 57016 333 55300 20000 85/06", "wgustm": "", "wspdi": "4.6", "wspdm": "7.4"}, {"heatindexm": "-9999", "windchillm": "-999", "wdire": "ENE", "wdird": "70", "windchilli": "-999", "hail": "0", "heatindexi": "-9999", "precipi": "", "thunder": "0", "pressurei": "30.16", "snow": "0", "pressurem": "1021", "fog": "0", "icon": "cloudy", "precipm": "", "conds": "Overcast", "tornado": "0", "hum": "98", "tempi": "55", "tempm": "13", "dewptm": "13", "rain": "0", "dewpti": "55", "date": {"mday": "05", "hour": "05", "min": "00", "mon": "09", "pretty": "5:00 AM CEST on September 05, 2014", "year": "2014", "tzname": "Europe/Copenhagen"}, "visi": "7", "vism": "11", "utcdate": {"mday": "05", "hour": "03", "min": "00", "mon": "09", "pretty": "3:00 AM GMT on September 05, 2014", "year": "2014", "tzname": "UTC"}, "wgusti": "", "metar": "AAXX 05034 06156 25261 80704 10129 20126 30196 40212 57014 333 55300 20000 6///7 88/05", "wgustm": "", "wspdi": "4.6", "wspdm": "7.4"}, {"heatindexm": "-9999", "windchillm": "-999", "wdire": "ENE", "wdird": "70", "windchilli": "-999", "hail": "0", "heatindexi": "-9999", "precipi": "", "thunder": "0", "pressurei": "30.14", "snow": "0", "pressurem": "1021", "fog": "0", "icon": "hazy", "precipm": "", "conds": "Mist", "tornado": "0", "hum": "98", "tempi": "55", "tempm": "13", "dewptm": "13", "rain": "0", "dewpti": "55", "date": {"mday": "05", "hour": "06", "min": "00", "mon": "09", "pretty": "6:00 AM CEST on September 05, 2014", "year": "2014", "tzname": "Europe/Copenhagen"}, "visi": "4", "vism": "7", "utcdate": {"mday": "05", "hour": "04", "min": "00", "mon": "09", "pretty": "4:00 AM GMT on September 05, 2014", "year": "2014", "tzname": "UTC"}, "wgusti": "", "metar": "AAXX 05044 06156 47257 80703 10127 20126 30191 40207 57014 71010 333 55300 20000 88/05", "wgustm": "", "wspdi": "3.5", "wspdm": "5.6"}, {"heatindexm": "-9999", "windchillm": "-999", "wdire": "East", "wdird": "90", "windchilli": "-999", "hail": "0", "heatindexi": "-9999", "precipi": "", "thunder": "0", "pressurei": "30.13", "snow": "0", "pressurem": "1020", "fog": "0", "icon": "hazy", "precipm": "", "conds": "Mist", "tornado": "0", "hum": "100", "tempi": "56", "tempm": "14", "dewptm": "14", "rain": "0", "dewpti": "56", "date": {"mday": "05", "hour": "07", "min": "00", "mon": "09", "pretty": "7:00 AM CEST on September 05, 2014", "year": "2014", "tzname": "Europe/Copenhagen"}, "visi": "4", "vism": "7", "utcdate": {"mday": "05", "hour": "05", "min": "00", "mon": "09", "pretty": "5:00 AM GMT on September 05, 2014", "year": "2014", "tzname": "UTC"}, "wgusti": "", "metar": "AAXX 05054 06156 47257 80904 10136 20136 30187 40203 57012 71011 333 55300 20018 88/04", "wgustm": "", "wspdi": "4.6", "wspdm": "7.4"}, {"heatindexm": "-9999", "windchillm": "-999", "wdire": "East", "wdird": "90", "windchilli": "-999", "hail": "0", "heatindexi": "-9999", "precipi": "", "thunder": "0", "pressurei": "30.12", "snow": "0", "pressurem": "1020", "fog": "0", "icon": "hazy", "precipm": "", "conds": "Mist", "tornado": "0", "hum": "96", "tempi": "58", "tempm": "14", "dewptm": "14", "rain": "0", "dewpti": "57", "date": {"mday": "05", "hour": "08", "min": "00", "mon": "09", "pretty": "8:00 AM CEST on September 05, 2014", "year": "2014", "tzname": "Europe/Copenhagen"}, "visi": "5", "vism": "8", "utcdate": {"mday": "05", "hour": "06", "min": "00", "mon": "09", "pretty": "6:00 AM GMT on September 05, 2014", "year": "2014", "tzname": "UTC"}, "wgusti": "", "metar": "AAXX 05064 06156 07258 80905 10142 20140 30184 40200 57012 6///2 71010 333 10160 20111 55300 20173 6///7 70000 88/04", "wgustm": "", "wspdi": "5.8", "wspdm": "9.3"}, {"heatindexm": "-9999", "windchillm": "-999", "wdire": "East", "wdird": "100", "windchilli": "-999", "hail": "0", "heatindexi": "-9999", "precipi": "", "thunder": "0", "pressurei": "30.12", "snow": "0", "pressurem": "1020", "fog": "0", "icon": "clear", "precipm": "", "conds": "Clear", "tornado": "0", "hum": "94", "tempi": "60", "tempm": "16", "dewptm": "15", "rain": "0", "dewpti": "59", "date": {"mday": "05", "hour": "09", "min": "00", "mon": "09", "pretty": "9:00 AM CEST on September 05, 2014", "year": "2014", "tzname": "Europe/Copenhagen"}, "visi": "7", "vism": "12", "utcdate": {"mday": "05", "hour": "07", "min": "00", "mon": "09", "pretty": "7:00 AM GMT on September 05, 2014", "year": "2014", "tzname": "UTC"}, "wgusti": "", "metar": "AAXX 05074 06156 47262 51005 10157 20149 30182 40199 57009 70010 333 55304 20598 85/05", "wgustm": "", "wspdi": "5.8", "wspdm": "9.3"}, {"heatindexm": "-9999", "windchillm": "-999", "wdire": "East", "wdird": "100", "windchilli": "-999", "hail": "0", "heatindexi": "-9999", "precipi": "", "thunder": "0", "pressurei": "30.12", "snow": "0", "pressurem": "1020", "fog": "0", "icon": "", "precipm": "", "conds": "", "tornado": "0", "hum": "82", "tempi": "64", "tempm": "18", "dewptm": "16", "rain": "0", "dewpti": "60", "date": {"mday": "05", "hour": "10", "min": "00", "mon": "09", "pretty": "10:00 AM CEST on September 05, 2014", "year": "2014", "tzname": "Europe/Copenhagen"}, "visi": "12", "vism": "19", "utcdate": {"mday": "05", "hour": "08", "min": "00", "mon": "09", "pretty": "8:00 AM GMT on September 05, 2014", "year": "2014", "tzname": "UTC"}, "wgusti": "", "metar": "AAXX 05084 06156 45/69 01006 10176 20155 30181 40197 57006 333 55310 21296", "wgustm": "", "wspdi": "6.9", "wspdm": "11.1"}, {"heatindexm": "-9999", "windchillm": "-999", "wdire": "East", "wdird": "90", "windchilli": "-999", "hail": "0", "heatindexi": "-9999", "precipi": "", "thunder": "0", "pressurei": "30.10", "snow": "0", "pressurem": "1019", "fog": "0", "icon": "clear", "precipm": "", "conds": "Clear", "tornado": "0", "hum": "73", "tempi": "67", "tempm": "20", "dewptm": "16", "rain": "0", "dewpti": "60", "date": {"mday": "05", "hour": "11", "min": "00", "mon": "09", "pretty": "11:00 AM CEST on September 05, 2014", "year": "2014", "tzname": "Europe/Copenhagen"}, "visi": "16", "vism": "25", "utcdate": {"mday": "05", "hour": "09", "min": "00", "mon": "09", "pretty": "9:00 AM GMT on September 05, 2014", "year": "2014", "tzname": "UTC"}, "wgusti": "", "metar": "AAXX 05094 06156 27/75 00907 10195 20158 30177 40193 57007 70010 333 55308 21552 6///7", "wgustm": "", "wspdi": "8.1", "wspdm": "13.0"}, {"heatindexm": "-9999", "windchillm": "-999", "wdire": "East", "wdird": "80", "windchilli": "-999", "hail": "0", "heatindexi": "-9999", "precipi": "", "thunder": "0", "pressurei": "30.09", "snow": "0", "pressurem": "1019", "fog": "0", "icon": "", "precipm": "", "conds": "", "tornado": "0", "hum": "63", "tempi": "70", "tempm": "21", "dewptm": "16", "rain": "0", "dewpti": "60", "date": {"mday": "05", "hour": "12", "min": "00", "mon": "09", "pretty": "12:00 PM CEST on September 05, 2014", "year": "2014", "tzname": "Europe/Copenhagen"}, "visi": "22", "vism": "35", "utcdate": {"mday": "05", "hour": "10", "min": "00", "mon": "09", "pretty": "10:00 AM GMT on September 05, 2014", "year": "2014", "tzname": "UTC"}, "wgusti": "", "metar": "AAXX 05104 06156 45/81 00810 10212 20156 30174 40190 57008 333 55310 22070", "wgustm": "", "wspdi": "11.5", "wspdm": "18.5"}, {"heatindexm": "-9999", "windchillm": "-999", "wdire": "East", "wdird": "100", "windchilli": "-999", "hail": "0", "heatindexi": "-9999", "precipi": "", "thunder": "0", "pressurei": "30.08", "snow": "0", "pressurem": "1019", "fog": "0", "icon": "", "precipm": "", "conds": "", "tornado": "0", "hum": "54", "tempi": "72", "tempm": "22", "dewptm": "15", "rain": "0", "dewpti": "59", "date": {"mday": "05", "hour": "13", "min": "00", "mon": "09", "pretty": "1:00 PM CEST on September 05, 2014", "year": "2014", "tzname": "Europe/Copenhagen"}, "visi": "18", "vism": "29", "utcdate": {"mday": "05", "hour": "11", "min": "00", "mon": "09", "pretty": "11:00 AM GMT on September 05, 2014", "year": "2014", "tzname": "UTC"}, "wgusti": "", "metar": "AAXX 05114 06156 45/79 01010 10220 20148 30170 40186 57011 333 55310 22117", "wgustm": "", "wspdi": "11.5", "wspdm": "18.5"}, {"heatindexm": "-9999", "windchillm": "-999", "wdire": "ESE", "wdird": "110", "windchilli": "-999", "hail": "0", "heatindexi": "-9999", "precipi": "", "thunder": "0", "pressurei": "30.07", "snow": "0", "pressurem": "1018", "fog": "0", "icon": "clear", "precipm": "", "conds": "Clear", "tornado": "0", "hum": "49", "tempi": "73", "tempm": "23", "dewptm": "14", "rain": "0", "dewpti": "58", "date": {"mday": "05", "hour": "14", "min": "00", "mon": "09", "pretty": "2:00 PM CEST on September 05, 2014", "year": "2014", "tzname": "Europe/Copenhagen"}, "visi": "19", "vism": "30", "utcdate": {"mday": "05", "hour": "12", "min": "00", "mon": "09", "pretty": "12:00 PM GMT on September 05, 2014", "year": "2014", "tzname": "UTC"}, "wgusti": "", "metar": "AAXX 05124 06156 07/80 01113 10227 20143 30166 40182 57011 6///1 70010 333 55310 22192 6///7", "wgustm": "", "wspdi": "15.0", "wspdm": "24.1"}, {"heatindexm": "-9999", "windchillm": "-999", "wdire": "East", "wdird": "100", "windchilli": "-999", "hail": "0", "heatindexi": "-9999", "precipi": "", "thunder": "0", "pressurei": "30.05", "snow": "0", "pressurem": "1018", "fog": "0", "icon": "", "precipm": "", "conds": "", "tornado": "0", "hum": "51", "tempi": "73", "tempm": "23", "dewptm": "15", "rain": "0", "dewpti": "59", "date": {"mday": "05", "hour": "15", "min": "00", "mon": "09", "pretty": "3:00 PM CEST on September 05, 2014", "year": "2014", "tzname": "Europe/Copenhagen"}, "visi": "17", "vism": "28", "utcdate": {"mday": "05", "hour": "13", "min": "00", "mon": "09", "pretty": "1:00 PM GMT on September 05, 2014", "year": "2014", "tzname": "UTC"}, "wgusti": "", "metar": "AAXX 05134 06156 45/78 01013 10227 20148 30160 40175 57014 333 55310 22106", "wgustm": "", "wspdi": "15.0", "wspdm": "24.1"}, {"heatindexm": "-9999", "windchillm": "-999", "wdire": "East", "wdird": "100", "windchilli": "-999", "hail": "0", "heatindexi": "-9999", "precipi": "", "thunder": "0", "pressurei": "30.04", "snow": "0", "pressurem": "1017", "fog": "0", "icon": "partlycloudy", "precipm": "", "conds": "Scattered Clouds", "tornado": "0", "hum": "52", "tempi": "72", "tempm": "22", "dewptm": "14", "rain": "0", "dewpti": "58", "date": {"mday": "05", "hour": "16", "min": "00", "mon": "09", "pretty": "4:00 PM CEST on September 05, 2014", "year": "2014", "tzname": "Europe/Copenhagen"}, "visi": "8", "vism": "13", "utcdate": {"mday": "05", "hour": "14", "min": "00", "mon": "09", "pretty": "2:00 PM GMT on September 05, 2014", "year": "2014", "tzname": "UTC"}, "wgusti": "", "metar": "AAXX 05144 06156 45963 11012 10222 20144 30156 40171 57014 333 55310 21739 81/74 91123", "wgustm": "", "wspdi": "13.8", "wspdm": "22.2"}, {"heatindexm": "-9999", "windchillm": "-999", "wdire": "East", "wdird": "100", "windchilli": "-999", "hail": "0", "heatindexi": "-9999", "precipi": "", "thunder": "0", "pressurei": "30.04", "snow": "0", "pressurem": "1017", "fog": "0", "icon": "", "precipm": "", "conds": "", "tornado": "0", "hum": "48", "tempi": "70", "tempm": "21", "dewptm": "12", "rain": "0", "dewpti": "54", "date": {"mday": "05", "hour": "17", "min": "00", "mon": "09", "pretty": "5:00 PM CEST on September 05, 2014", "year": "2014", "tzname": "Europe/Copenhagen"}, "visi": "22", "vism": "35", "utcdate": {"mday": "05", "hour": "15", "min": "00", "mon": "09", "pretty": "3:00 PM GMT on September 05, 2014", "year": "2014", "tzname": "UTC"}, "wgusti": "", "metar": "AAXX 05154 06156 25/81 01010 10209 20125 30154 40170 57012 333 55301 20788 6///7 91123", "wgustm": "", "wspdi": "11.5", "wspdm": "18.5"}, {"heatindexm": "-9999", "windchillm": "-999", "wdire": "East", "wdird": "100", "windchilli": "-999", "hail": "0", "heatindexi": "-9999", "precipi": "", "thunder": "0", "pressurei": "30.03", "snow": "0", "pressurem": "1017", "fog": "0", "icon": "partlycloudy", "precipm": "", "conds": "Scattered Clouds", "tornado": "0", "hum": "49", "tempi": "69", "tempm": "20", "dewptm": "12", "rain": "0", "dewpti": "54", "date": {"mday": "05", "hour": "18", "min": "00", "mon": "09", "pretty": "6:00 PM CEST on September 05, 2014", "year": "2014", "tzname": "Europe/Copenhagen"}, "visi": "25", "vism": "40", "utcdate": {"mday": "05", "hour": "16", "min": "00", "mon": "09", "pretty": "4:00 PM GMT on September 05, 2014", "year": "2014", "tzname": "UTC"}, "wgusti": "", "metar": "AAXX 05164 06156 45982 11010 10203 20123 30152 40168 57008 333 55303 20688 81/71", "wgustm": "", "wspdi": "11.5", "wspdm": "18.5"}, {"heatindexm": "-9999", "windchillm": "-999", "wdire": "East", "wdird": "100", "windchilli": "-999", "hail": "0", "heatindexi": "-9999", "precipi": "", "thunder": "0", "pressurei": "30.02", "snow": "0", "pressurem": "1016", "fog": "0", "icon": "partlycloudy", "precipm": "", "conds": "Scattered Clouds", "tornado": "0", "hum": "52", "tempi": "67", "tempm": "20", "dewptm": "12", "rain": "0", "dewpti": "53", "date": {"mday": "05", "hour": "19", "min": "00", "mon": "09", "pretty": "7:00 PM CEST on September 05, 2014", "year": "2014", "tzname": "Europe/Copenhagen"}, "visi": "25", "vism": "40", "utcdate": {"mday": "05", "hour": "17", "min": "00", "mon": "09", "pretty": "5:00 PM GMT on September 05, 2014", "year": "2014", "tzname": "UTC"}, "wgusti": "", "metar": "AAXX 05174 06156 45982 11011 10195 20118 30149 40165 57007 333 55302 20313 81/74", "wgustm": "", "wspdi": "12.7", "wspdm": "20.4"}, {"heatindexm": "-9999", "windchillm": "-999", "wdire": "East", "wdird": "100", "windchilli": "-999", "hail": "0", "heatindexi": "-9999", "precipi": "", "thunder": "0", "pressurei": "30.01", "snow": "0", "pressurem": "1016", "fog": "0", "icon": "partlycloudy", "precipm": "", "conds": "Scattered Clouds", "tornado": "0", "hum": "58", "tempi": "65", "tempm": "18", "dewptm": "12", "rain": "0", "dewpti": "54", "date": {"mday": "05", "hour": "20", "min": "00", "mon": "09", "pretty": "8:00 PM CEST on September 05, 2014", "year": "2014", "tzname": "Europe/Copenhagen"}, "visi": "28", "vism": "45", "utcdate": {"mday": "05", "hour": "18", "min": "00", "mon": "09", "pretty": "6:00 PM GMT on September 05, 2014", "year": "2014", "tzname": "UTC"}, "wgusti": "", "metar": "AAXX 05184 06156 05983 11010 10184 20121 30147 40163 57007 6///2 333 10229 20141 55306 20187 6///7 81/71 91123", "wgustm": "", "wspdi": "11.5", "wspdm": "18.5"}, {"heatindexm": "-9999", "windchillm": "-999", "wdire": "East", "wdird": "100", "windchilli": "-999", "hail": "0", "heatindexi": "-9999", "precipi": "", "thunder": "0", "pressurei": "30.02", "snow": "0", "pressurem": "1016", "fog": "0", "icon": "", "precipm": "", "conds": "", "tornado": "0", "hum": "69", "tempi": "63", "tempm": "17", "dewptm": "13", "rain": "0", "dewpti": "55", "date": {"mday": "05", "hour": "21", "min": "00", "mon": "09", "pretty": "9:00 PM CEST on September 05, 2014", "year": "2014", "tzname": "Europe/Copenhagen"}, "visi": "22", "vism": "35", "utcdate": {"mday": "05", "hour": "19", "min": "00", "mon": "09", "pretty": "7:00 PM GMT on September 05, 2014", "year": "2014", "tzname": "UTC"}, "wgusti": "", "metar": "AAXX 05194 06156 45/81 01007 10171 20129 30148 40164 57004 333 55300 20000", "wgustm": "", "wspdi": "8.1", "wspdm": "13.0"}, {"heatindexm": "-9999", "windchillm": "-999", "wdire": "East", "wdird": "100", "windchilli": "-999", "hail": "0", "heatindexi": "-9999", "precipi": "", "thunder": "0", "pressurei": "30.02", "snow": "0", "pressurem": "1016", "fog": "0", "icon": "partlycloudy", "precipm": "", "conds": "Scattered Clouds", "tornado": "0", "hum": "77", "tempi": "62", "tempm": "16", "dewptm": "14", "rain": "0", "dewpti": "56", "date": {"mday": "05", "hour": "22", "min": "00", "mon": "09", "pretty": "10:00 PM CEST on September 05, 2014", "year": "2014", "tzname": "Europe/Copenhagen"}, "visi": "17", "vism": "28", "utcdate": {"mday": "05", "hour": "20", "min": "00", "mon": "09", "pretty": "8:00 PM GMT on September 05, 2014", "year": "2014", "tzname": "UTC"}, "wgusti": "", "metar": "AAXX 05204 06156 45978 11007 10165 20136 30148 40164 57001 333 55300 20000 81/66", "wgustm": "", "wspdi": "8.1", "wspdm": "13.0"}, {"heatindexm": "-9999", "windchillm": "-999", "wdire": "ESE", "wdird": "110", "windchilli": "-999", "hail": "0", "heatindexi": "-9999", "precipi": "", "thunder": "0", "pressurei": "30.01", "snow": "0", "pressurem": "1016", "fog": "0", "icon": "partlycloudy", "precipm": "", "conds": "Partly Cloudy", "tornado": "0", "hum": "82", "tempi": "61", "tempm": "16", "dewptm": "14", "rain": "0", "dewpti": "57", "date": {"mday": "05", "hour": "23", "min": "00", "mon": "09", "pretty": "11:00 PM CEST on September 05, 2014", "year": "2014", "tzname": "Europe/Copenhagen"}, "visi": "16", "vism": "26", "utcdate": {"mday": "05", "hour": "21", "min": "00", "mon": "09", "pretty": "9:00 PM GMT on September 05, 2014", "year": "2014", "tzname": "UTC"}, "wgusti": "", "metar": "AAXX 05214 06156 25976 31107 10162 20139 30147 40163 54000 333 55300 20000 6///7 83/66", "wgustm": "", "wspdi": "8.1", "wspdm": "13.0"}], "dailysummary": [{"maxpressurem": "1024", "maxdewptm": "16", "maxpressurei": "30.23", "maxdewpti": "60", "since1julheatingdegreedaysnormal": "", "heatingdegreedaysnormal": "", "since1sepcoolingdegreedaysnormal": "", "hail": "0", "since1julsnowfallm": "", "date": {"mday": "05", "hour": "00", "min": "00", "mon": "09", "pretty": "12:00 AM CEST on September 05, 2014", "year": "2014", "tzname": "Europe/Copenhagen"}, "since1julheatingdegreedays": "", "maxvisi": "19.0", "since1sepheatingdegreedaysnormal": "", "heatingdegreedays": "2", "mindewptm": "11", "since1sepheatingdegreedays": "", "maxwspdm": "24", "since1julsnowfalli": "", "since1sepcoolingdegreedays": "", "snow": "0", "meanvism": "18.7", "meandewptm": "13", "snowdepthm": "", "meanvisi": "11.6", "fog": "0", "snowdepthi": "", "minvism": "7.0", "since1jancoolingdegreedays": "", "minvisi": "4.0", "coolingdegreedaysnormal": "", "gdegreedays": "12", "maxwspdi": "15", "meanwindspdi": "7", "meanpressurei": "30.10", "monthtodateheatingdegreedaysnormal": "", "meanwindspdm": "11", "meanpressurem": "1019.17", "tornado": "0", "mindewpti": "52", "mintempi": "52", "meandewpti": "56", "rain": "0", "mintempm": "11", "minhumidity": "48", "precipsource": "3Or6HourObs", "minwspdi": "4", "meanwdird": "-1", "meanwdire": "Variable", "minwspdm": "6", "monthtodatesnowfalli": "", "monthtodatecoolingdegreedaysnormal": "", "monthtodatesnowfallm": "", "maxhumidity": "100", "coolingdegreedays": "0", "maxtempm": "22", "minpressurei": "30.01", "monthtodatecoolingdegreedays": "", "maxtempi": "73", "minpressurem": "1016", "humidity": "75", "precipi": "0.00", "snowfalli": "", "since1jancoolingdegreedaysnormal": "", "precipm": "0.0", "snowfallm": "", "thunder": "0", "monthtodateheatingdegreedays": "", "meantempi": "62", "maxvism": "30.0", "meantempm": "16"}]}}